tonic/__init__.py
tonic/config.py
tonic_config-0.1.7.dist-info/LICENSE
tonic_config-0.1.7.dist-info/METADATA
tonic_config-0.1.7.dist-info/WHEEL
tonic_config-0.1.7.dist-info/top_level.txt
tonic_config-0.1.7.dist-info/RECORD
