Metadata-Version: 2.1
Name: tonic-config
Version: 0.1.7
Summary: Lightweight configuration framework for Python, combining the most notable aspects of Gin and Sacred.
Home-page: https://github.com/nmichlo/tonic-config
Author: Nathan Michlo
Author-email: NathanJMichlo@gmail.com
License: UNKNOWN
Platform: UNKNOWN
Classifier: License :: OSI Approved :: MIT License
Classifier: Programming Language :: Python :: 3.6
Classifier: Programming Language :: Python :: 3.7
Classifier: Programming Language :: Python :: 3.8
Classifier: Operating System :: OS Independent
Classifier: Development Status :: 3 - Alpha
Classifier: Intended Audience :: Developers
Classifier: Intended Audience :: Science/Research
Classifier: Topic :: Scientific/Engineering :: Artificial Intelligence
Classifier: Topic :: Utilities
Requires-Python: >=3.6
Requires-Dist: toml
Requires-Dist: cached-property
